Metadata-Version: 2.1
Name: arpa2.shell.dns
Version: 0.0.3
Summary: The ARPA2 Shell for DNS
Home-page: https://github.com/arpa2/arpa2shell/tree/master/src/arpa2dns
Author: Rick van Rein (for the ARPA2 Shell project)
Author-email: rick@openfortress.nl
License: UNKNOWN
Platform: UNKNOWN
Requires-Dist: arpa2.shell
Requires-Dist: libknot
